codi_mun_datamodels/__init__.py
codi_mun_datamodels/accruals/__init__.py
codi_mun_datamodels/employees/__init__.py
codi_mun_datamodels-0.0.1.dist-info/WHEEL
codi_mun_datamodels-0.0.1.dist-info/METADATA
codi_mun_datamodels-0.0.1.dist-info/RECORD
